litestar_socketify/__init__.py
litestar_socketify/__metadata__.py
litestar_socketify/cli.py
litestar_socketify/plugin.py
litestar_socketify-0.1.1.dist-info/METADATA
litestar_socketify-0.1.1.dist-info/WHEEL
litestar_socketify-0.1.1.dist-info/licenses/LICENSE
litestar_socketify-0.1.1.dist-info/RECORD
